{
  "id": "REQ-VL-031",
  "statement": "Approval workflow complexity — MVP includes approval as a status/action, but does not need a full — Status action, validation, lock behavior.",
  "governance": "approved",
  "maturity": "logic-defined",
  "delivery": "not-assessed",
  "source_id": "VL-031",
  "source_category": "Lifecycle & Version Status Rules",
  "priority": "MVP",
  "status": "Confirmed",
  "chain_layer": "REQ->BHV->RSP",
  "dependencies": "Permissions, communication date",
  "related_requirements": "Permissions & Access Control",
  "affected_modules": "src/types/lifecycle.ts; src/rules/lifecycle.rules.ts; src/services/versions.service.ts; status transition handlers",
  "ux_impact": "PM has a clear approve action without heavy",
  "risk": "Low-medium",
  "provenance": {
    "source": "dcx-requirements-master.csv",
    "source_path": "dcx-requirements-master.csv",
    "source_anchor": "VL-031",
    "authoring_actor": "RS-R6 migration",
    "confidence": 0.95,
    "confirmation_status": "confirmed",
    "last_checked_date": "2026-06-29"
  },
  "type": "Requirement",
  "scope": "product"
}
